LICENSE
MANIFEST.in
README.rst
pytest_collect_info_plugin.py
setup.py
pytest_collect_interface_info_plugin.egg-info/PKG-INFO
pytest_collect_interface_info_plugin.egg-info/SOURCES.txt
pytest_collect_interface_info_plugin.egg-info/dependency_links.txt
pytest_collect_interface_info_plugin.egg-info/entry_points.txt
pytest_collect_interface_info_plugin.egg-info/requires.txt
pytest_collect_interface_info_plugin.egg-info/top_level.txt
tests/test_collect_info_plugin.py