Metadata-Version: 2.1
Name: pytest-collect-interface-info-plugin
Version: 1.0.7
Summary: Get executed interface information in pytest interface automation framework
Home-page: https://github.com/LightOffX/pytest-collect_info_plugin
Author: LightOffX
Author-email: 
Maintainer: LightOffX
Maintainer-email: 
License: BSD-3
Classifier: Development Status :: 4 - Beta
Classifier: Framework :: Pytest
Classifier: Intended Audience :: Developers
Classifier: Topic :: Software Development :: Testing
Classifier: Programming Language :: Python
Classifier: Programming Language :: Python :: 3
Classifier: Programming Language :: Python :: 3.5
Classifier: Programming Language :: Python :: 3.6
Classifier: Programming Language :: Python :: 3.7
Classifier: Programming Language :: Python :: 3.8
Classifier: Programming Language :: Python :: 3 :: Only
Classifier: Programming Language :: Python :: Implementation :: CPython
Classifier: Programming Language :: Python :: Implementation :: PyPy
Classifier: Operating System :: OS Independent
Classifier: License :: OSI Approved :: BSD License
Requires-Python: >=3.5
License-File: LICENSE
